FalconEye/__init__.py
FalconEye/flatten.py
FalconEye/transform.py
FalconEye/walk.py
falconeye-0.3.0.dist-info/METADATA
falconeye-0.3.0.dist-info/WHEEL
falconeye-0.3.0.dist-info/licenses/LICENSE
falconeye-0.3.0.dist-info/RECORD
