Metadata-Version: 2.1
Name: FalconEye
Version: 0.3.0
Summary: Toolset for Data Exploration
Project-URL: Homepage, https://github.com/msherburne/FalconEye
Author-email: Mathieu Sherburne <mathieusherburne@outlook.com>
License: Copyright © 2022
License-File: LICENSE
Classifier: License :: OSI Approved :: MIT License
Classifier: Operating System :: OS Independent
Classifier: Programming Language :: Python :: 3
Requires-Python: >=3.6
Requires-Dist: pandas>=1.0.0
Requires-Dist: uuid>=1.30
